vizir/__init__.py
vizir/app.py
vizir/data.py
vizir/index.py
vizir/logic.py
vizir-0.8.dist-info/DESCRIPTION.rst
vizir-0.8.dist-info/METADATA
vizir-0.8.dist-info/RECORD
vizir-0.8.dist-info/WHEEL
vizir-0.8.dist-info/metadata.json
vizir-0.8.dist-info/top_level.txt
