Metadata-Version: 2.0
Name: vizir
Version: 0.8
Summary: Interface for visualize and compare machine learning experiences
Home-page: https://github.com/VincSP/Vizir
Author: VincSP
Author-email: vincent.serepeyrigain@viacesi.fr
License: MIT
Platform: UNKNOWN
